{
  "festHeads": [
    {
      "name": "Yug Agarwal",
      "designation": "Fest Head",
      "image": "/Team - YUG AGARWAL.jpg",
      "linkedin": "https://www.linkedin.com/in/alicejohnson",
      "email": "alice.johnson@example.com",
      "instagram": "https://www.instagram.com/yug_agarwal?igsh=MTZnNjc0amg2dnpmZA%3D%3D&utm_source=qr"
    },
    {
      "name": "Rajat Sharma",
      "designation": "Fest Head",
      "image": "/Team-Rajat-Sharma.jpg",
      "linkedin": "https://www.linkedin.com/in/michaelsmith",
      "email": "michael.smith@example.com",
      "instagram": "https://www.instagram.com/_rajat_srma?igsh=MXNhOHpnMm1kY2t3dw=="
    }
  ],
  "uiUx": [
    {
      "name": "Shourya Gupta",
      "designation": "Design head",
      "image": "/Team-Shourya.jpeg",
      "linkedin": "https://www.linkedin.com/in/michaelsmith",
      "email": "michael.smith@example.com",
      "instagram": "https://www.instagram.com/michaelsmith"
    }
  ],
  "publicRelations": [
    {
      "name": "Ayush Singh Chauhan",
      "designation": "Public Relation Head",
      "image": "/Team- AYUSH SINGH CHAUHAN.jpeg",
      "linkedin": "https://www.linkedin.com/in/alicejohnson",
      "email": "alice.johnson@example.com",
      "instagram": "https://www.instagram.com/ayush_s_c_/"
    },
    {
      "name": "Arnav",
      "designation": "Public Relation Head",
      "image": "/Team-Arnav.jpeg",
      "linkedin": "https://www.linkedin.com/in/alicejohnson",
      "email": "alice.johnson@example.com",
      "instagram": "https://www.instagram.com/spaghetti_luigi?igsh=aDc3ZGJyOTd6NHhu&utm_source=qrhttps://www.instagram.com/rss_7897?igsh=Z2hldWVxYzliYzl3&utm_source=qr"
    }
  ],
  "eventManagement": [
    {
      "name": "Ravindra Singh Shekhawat",
      "designation": "Event Management Head",
      "image": "/Team - RAVINDRA SINGH SHEKHAWAT.jpeg",
      "linkedin": "https://www.linkedin.com/in/alicejohnson",
      "email": "alice.johnson@example.com",
      "instagram": "https://www.instagram.com/rss_7897?igsh=Z2hldWVxYzliYzl3&utm_source=qr"
    },
    {
      
        "name": "Yogya",
        "designation": "Event Management Head",
        "image": "/Team - Yogya.jpg",
        "linkedin": "https://www.linkedin.com/in/alicejohnson",
        "email": "alice.johnson@example.com",
        "instagram": "https://www.instagram.com/yogya243?igsh=MTgyN2tvbjM2aGQzYg=="
      
    }
  ],
  "creative": [
    {
      "name": "Akshat Manas",
      "designation": "Creative Head",
      "image": "/Team - AKSHAT MANAS.jpg",
      "linkedin": "https://www.linkedin.com/in/johndoe",
      "email": "john.doe@example.com",
      "instagram": "https://www.instagram.com/it_wasnt_aksman?igsh=MWhsZDRxZ2NheXh2Zg=="
    },
    {
      "name": "Radhika Garg",
      "designation": "Creative Head",
      "image": "/Team- RADHIKA.jpeg",
      "linkedin": "https://www.linkedin.com/in/johndoe",
      "email": "john.doe@example.com",
      "instagram": "https://www.instagram.com/radhika._garg09?igsh=MWZna3BmZm03Y3dvcQ%3D%3D&utm_source=qr"
    }
  ],
  "sponsorship": [
    {
      "name": "Atharva Gulajkar",
      "designation": "Sponsorship Head",
      "image": "/Team - ATHARVA GULAJKAR.jpeg",
      "linkedin": "https://www.linkedin.com/in/michaelsmith",
      "email": "michael.smith@example.com",
      "instagram": "https://www.instagram.com/atharwahhh?igsh=MWZ6dHJpMTdvbHU3Mg%3D%3D&utm_source=qr"
    },
    {
     "name": "Ayush Pandey",
      "designation": "Sponsorship Head",
      "image": "/Team-AYUSH.jpg",
      "linkedin": "https://www.linkedin.com/in/michaelsmith",
      "email": "michael.smith@example.com",
      "instagram": "https://www.instagram.com/ayush8819?igsh=MTducWw3ajZ1bTAzYQ==" 
    },
    {
      "name": "Aryan Duhoon",
       "designation": "Sponsorship Head",
       "image": "/Team-ARYAN.jpg",
       "linkedin": "https://www.linkedin.com/in/michaelsmith",
       "email": "michael.smith@example.com",
       "instagram": "https://www.instagram.com/michaelsmith" 
     },
     {
      "name": "Ansh mehta",
       "designation": "Sponsorship Head",
       "image": "/Team-ANSH.jpeg",
       "linkedin": "https://www.linkedin.com/in/michaelsmith",
       "email": "michael.smith@example.com",
       "instagram": "https://www.instagram.com/anshmehta_22?igsh=aWI4YXlnZXR2ZWdh&utm_source=qr" 
     },
     {
      "name": "AKSHIT AGRAWAL",
       "designation": "Sponsorship Head",
       "image": "/Team-AKSHIT.jpg",
       "linkedin": "https://www.linkedin.com/in/michaelsmith",
       "email": "michael.smith@example.com",
       "instagram": "https://www.instagram.com/michaelsmith" 
     },
     {
      "name": "Sanidhya shankar pachauri",
       "designation": "Sponsorship Head",
       "image": "/Team- SANIDHYA.jpg",
       "linkedin": "https://www.linkedin.com/in/michaelsmith",
       "email": "michael.smith@example.com",
       "instagram": "https://www.instagram.com/sanidhya9790?igsh=MWZ2cWRjZzl3M2M2Zw==" 
     }
  ],
  "socialMedia": [
    {
      "name": "Anwita Sarangi",
      "designation": "Social Media Head",
      "image": "/Team- ANWITA SARANGI.jpg",
      "linkedin": "https://www.linkedin.com/in/michaelsmith",
      "email": "michael.smith@example.com",
      "instagram": "https://www.instagram.com/anwitasarangi?igsh=OTA2Mno3Z3l5b3Y0"
    }
  ],
  "developers": [
    {
      "name": "Srijan Das",
      "designation": "Development head",
      "image": "/srijan_despo.webp",
      "linkedin": "https://www.linkedin.com/in/michaelsmith",
      "email": "michael.smith@example.com",
      "instagram": "https://www.instagram.com/srijandas_"
    },
    {
      "name": "Siddharth Jiyani",
      "designation": "Development head",
      "image": "/siddharth.jpeg",
      "linkedin": "https://www.linkedin.com/in/michaelsmith",
      "email": "michael.smith@example.com",
      "instagram": "https://www.instagram.com/siddharth_jiyani"
    },
    {
      "name": "Swaraj Layek",
      "designation": "Development head",
      "image": "/swaraj_randi.jpeg",
      "linkedin": "https://www.linkedin.com/in/michaelsmith",
      "email": "michael.smith@example.com",
      "instagram": "https://www.instagram.com/swaraj_layek_"
    }
  ],
  "TC": [
    {
      "name": "Shivansh Porwal",
      "designation": "General Secretary",
      "image": "/Team-Shivansh.jpg",
      "linkedin": "https://www.linkedin.com/in/emmawilliams",
      "email": "emma.williams@example.com",
      "instagram": "https://www.instagram.com/shivansh_911?igsh=bXFiOXJlbm1jaWJr"
    },
    {
      "name": "Prakhar Kesharwani",
      "designation": "Finance Convenor",
      "image": "/Team- PRAKHAR KESHARWANI.jpeg",
      "linkedin": "https://www.linkedin.com/in/michaelsmith",
      "email": "michael.smith@example.com",
      "instagram": "https://www.instagram.com/14_prakhar?igsh=OTJkOWF4N3N3OWs%3D&utm_source=qr"
    },
    {
      "name": "Hiya Jain",
      "designation": "Associate General Secretary",
      "image": "/Team- HIYA JAIN.jpg",
      "linkedin": "https://www.linkedin.com/in/emmawilliams",
      "email": "emma.williams@example.com",
      "instagram": "https://www.instagram.com/jainhiya04?igsh=MWZwY2RyZGdlYmthbA=="
    }
  ]
}